<?xml version='1.0' encoding='utf-8'?>
<Gesture Name="K" NumPts="152">
  <Point X="668" Y="-505" T="1784057911143" />
  <Point X="668" Y="-504" T="1784057911272" />
  <Point X="668" Y="-488" T="1784057911294" />
  <Point X="668" Y="-454" T="1784057911308" />
  <Point X="668" Y="-411" T="1784057911325" />
  <Point X="668" Y="-365" T="1784057911342" />
  <Point X="668" Y="-321" T="1784057911358" />
  <Point X="668" Y="-279" T="1784057911375" />
  <Point X="668" Y="-242" T="1784057911393" />
  <Point X="668" Y="-209" T="1784057911408" />
  <Point X="668" Y="-178" T="1784057911426" />
  <Point X="668" Y="-149" T="1784057911446" />
  <Point X="668" Y="-129" T="1784057911460" />
  <Point X="668" Y="-114" T="1784057911475" />
  <Point X="668" Y="-95" T="1784057911509" />
  <Point X="668" Y="-91" T="1784057911529" />
  <Point X="668" Y="-88" T="1784057911542" />
  <Point X="668" Y="-87" T="1784057911561" />
  <Point X="668" Y="-86" T="1784057911594" />
  <Point X="668" Y="-85" T="1784057911610" />
  <Point X="668" Y="-84" T="1784057911628" />
  <Point X="668" Y="-80" T="1784057911643" />
  <Point X="668" Y="-74" T="1784057911660" />
  <Point X="668" Y="-67" T="1784057911675" />
  <Point X="668" Y="-59" T="1784057911693" />
  <Point X="667" Y="-51" T="1784057911710" />
  <Point X="667" Y="-43" T="1784057911726" />
  <Point X="666" Y="-38" T="1784057911742" />
  <Point X="666" Y="-34" T="1784057911759" />
  <Point X="666" Y="-32" T="1784057911775" />
  <Point X="666" Y="-30" T="1784057911792" />
  <Point X="666" Y="-28" T="1784057911808" />
  <Point X="666" Y="-30" T="1784057911909" />
  <Point X="666" Y="-32" T="1784057911927" />
  <Point X="665" Y="-35" T="1784057911942" />
  <Point X="665" Y="-39" T="1784057911962" />
  <Point X="665" Y="-43" T="1784057911975" />
  <Point X="665" Y="-47" T="1784057911992" />
  <Point X="664" Y="-51" T="1784057912008" />
  <Point X="664" Y="-60" T="1784057912042" />
  <Point X="664" Y="-67" T="1784057912076" />
  <Point X="664" Y="-69" T="1784057912092" />
  <Point X="664" Y="-72" T="1784057912110" />
  <Point X="663" Y="-78" T="1784057912127" />
  <Point X="662" Y="-86" T="1784057912143" />
  <Point X="661" Y="-95" T="1784057912158" />
  <Point X="661" Y="-102" T="1784057912176" />
  <Point X="661" Y="-108" T="1784057912194" />
  <Point X="661" Y="-112" T="1784057912208" />
  <Point X="660" Y="-115" T="1784057912226" />
  <Point X="660" Y="-119" T="1784057912242" />
  <Point X="660" Y="-125" T="1784057912258" />
  <Point X="660" Y="-133" T="1784057912275" />
  <Point X="660" Y="-140" T="1784057912294" />
  <Point X="660" Y="-144" T="1784057912309" />
  <Point X="660" Y="-148" T="1784057912326" />
  <Point X="660" Y="-151" T="1784057912362" />
  <Point X="660" Y="-156" T="1784057912376" />
  <Point X="660" Y="-166" T="1784057912395" />
  <Point X="660" Y="-173" T="1784057912410" />
  <Point X="660" Y="-179" T="1784057912427" />
  <Point X="660" Y="-183" T="1784057912446" />
  <Point X="660" Y="-185" T="1784057912460" />
  <Point X="660" Y="-186" T="1784057912475" />
  <Point X="660" Y="-187" T="1784057912494" />
  <Point X="660" Y="-188" T="1784057912508" />
  <Point X="660" Y="-189" T="1784057912526" />
  <Point X="660" Y="-190" T="1784057912542" />
  <Point X="660" Y="-191" T="1784057912559" />
  <Point X="660" Y="-192" T="1784057912576" />
  <Point X="661" Y="-193" T="1784057912608" />
  <Point X="664" Y="-197" T="1784057912642" />
  <Point X="667" Y="-203" T="1784057912660" />
  <Point X="673" Y="-213" T="1784057912676" />
  <Point X="684" Y="-229" T="1784057912692" />
  <Point X="694" Y="-243" T="1784057912709" />
  <Point X="701" Y="-252" T="1784057912727" />
  <Point X="707" Y="-259" T="1784057912742" />
  <Point X="711" Y="-266" T="1784057912760" />
  <Point X="717" Y="-273" T="1784057912778" />
  <Point X="728" Y="-288" T="1784057912795" />
  <Point X="742" Y="-306" T="1784057912808" />
  <Point X="766" Y="-334" T="1784057912842" />
  <Point X="776" Y="-345" T="1784057912860" />
  <Point X="785" Y="-356" T="1784057912875" />
  <Point X="809" Y="-385" T="1784057912909" />
  <Point X="839" Y="-416" T="1784057912943" />
  <Point X="853" Y="-429" T="1784057912961" />
  <Point X="865" Y="-440" T="1784057912976" />
  <Point X="874" Y="-448" T="1784057912993" />
  <Point X="887" Y="-457" T="1784057913009" />
  <Point X="900" Y="-466" T="1784057913027" />
  <Point X="912" Y="-473" T="1784057913042" />
  <Point X="922" Y="-480" T="1784057913059" />
  <Point X="929" Y="-484" T="1784057913075" />
  <Point X="933" Y="-487" T="1784057913092" />
  <Point X="934" Y="-488" T="1784057913109" />
  <Point X="935" Y="-488" T="1784057913177" />
  <Point X="934" Y="-486" T="1784057913193" />
  <Point X="929" Y="-480" T="1784057913229" />
  <Point X="924" Y="-475" T="1784057913243" />
  <Point X="920" Y="-471" T="1784057913261" />
  <Point X="913" Y="-464" T="1784057913276" />
  <Point X="902" Y="-454" T="1784057913294" />
  <Point X="889" Y="-440" T="1784057913310" />
  <Point X="872" Y="-423" T="1784057913328" />
  <Point X="852" Y="-404" T="1784057913343" />
  <Point X="832" Y="-385" T="1784057913359" />
  <Point X="816" Y="-369" T="1784057913375" />
  <Point X="801" Y="-355" T="1784057913393" />
  <Point X="788" Y="-340" T="1784057913408" />
  <Point X="778" Y="-328" T="1784057913426" />
  <Point X="769" Y="-317" T="1784057913442" />
  <Point X="752" Y="-296" T="1784057913476" />
  <Point X="744" Y="-284" T="1784057913494" />
  <Point X="735" Y="-271" T="1784057913508" />
  <Point X="727" Y="-259" T="1784057913526" />
  <Point X="721" Y="-251" T="1784057913543" />
  <Point X="717" Y="-246" T="1784057913560" />
  <Point X="716" Y="-244" T="1784057913585" />
  <Point X="716" Y="-243" T="1784057913593" />
  <Point X="716" Y="-242" T="1784057913643" />
  <Point X="718" Y="-242" T="1784057913663" />
  <Point X="721" Y="-240" T="1784057913676" />
  <Point X="733" Y="-225" T="1784057913709" />
  <Point X="745" Y="-207" T="1784057913743" />
  <Point X="764" Y="-184" T="1784057913795" />
  <Point X="772" Y="-176" T="1784057913810" />
  <Point X="779" Y="-168" T="1784057913828" />
  <Point X="786" Y="-162" T="1784057913843" />
  <Point X="793" Y="-156" T="1784057913861" />
  <Point X="799" Y="-151" T="1784057913877" />
  <Point X="805" Y="-146" T="1784057913894" />
  <Point X="811" Y="-141" T="1784057913909" />
  <Point X="817" Y="-137" T="1784057913929" />
  <Point X="823" Y="-131" T="1784057913943" />
  <Point X="830" Y="-125" T="1784057913960" />
  <Point X="836" Y="-119" T="1784057913976" />
  <Point X="841" Y="-114" T="1784057913993" />
  <Point X="846" Y="-109" T="1784057914009" />
  <Point X="850" Y="-106" T="1784057914026" />
  <Point X="853" Y="-103" T="1784057914044" />
  <Point X="856" Y="-101" T="1784057914061" />
  <Point X="857" Y="-99" T="1784057914077" />
  <Point X="858" Y="-98" T="1784057914095" />
  <Point X="860" Y="-97" T="1784057914109" />
  <Point X="861" Y="-96" T="1784057914127" />
  <Point X="864" Y="-94" T="1784057914142" />
  <Point X="866" Y="-91" T="1784057914160" />
  <Point X="868" Y="-89" T="1784057914177" />
  <Point X="870" Y="-87" T="1784057914194" />
  <Point X="871" Y="-86" T="1784057914210" />
</Gesture>