<?xml version='1.0' encoding='utf-8'?>
<Gesture Name="Z" NumPts="122">
  <Point X="637" Y="-565" T="1784058627518" />
  <Point X="638" Y="-565" T="1784058627651" />
  <Point X="643" Y="-565" T="1784058627668" />
  <Point X="655" Y="-565" T="1784058627684" />
  <Point X="671" Y="-565" T="1784058627701" />
  <Point X="691" Y="-565" T="1784058627718" />
  <Point X="730" Y="-565" T="1784058627751" />
  <Point X="744" Y="-565" T="1784058627771" />
  <Point X="754" Y="-565" T="1784058627787" />
  <Point X="760" Y="-565" T="1784058627805" />
  <Point X="765" Y="-565" T="1784058627820" />
  <Point X="768" Y="-565" T="1784058627837" />
  <Point X="772" Y="-565" T="1784058627852" />
  <Point X="780" Y="-565" T="1784058627870" />
  <Point X="791" Y="-565" T="1784058627888" />
  <Point X="805" Y="-564" T="1784058627906" />
  <Point X="818" Y="-563" T="1784058627919" />
  <Point X="831" Y="-561" T="1784058627937" />
  <Point X="843" Y="-559" T="1784058627952" />
  <Point X="852" Y="-558" T="1784058627970" />
  <Point X="860" Y="-556" T="1784058627985" />
  <Point X="867" Y="-555" T="1784058628003" />
  <Point X="873" Y="-555" T="1784058628018" />
  <Point X="886" Y="-554" T="1784058628084" />
  <Point X="887" Y="-553" T="1784058628102" />
  <Point X="887" Y="-552" T="1784058628151" />
  <Point X="885" Y="-550" T="1784058628168" />
  <Point X="881" Y="-549" T="1784058628184" />
  <Point X="877" Y="-546" T="1784058628201" />
  <Point X="871" Y="-543" T="1784058628217" />
  <Point X="865" Y="-540" T="1784058628235" />
  <Point X="855" Y="-535" T="1784058628250" />
  <Point X="842" Y="-525" T="1784058628268" />
  <Point X="824" Y="-511" T="1784058628284" />
  <Point X="805" Y="-495" T="1784058628303" />
  <Point X="791" Y="-482" T="1784058628318" />
  <Point X="782" Y="-474" T="1784058628335" />
  <Point X="763" Y="-457" T="1784058628370" />
  <Point X="757" Y="-451" T="1784058628385" />
  <Point X="748" Y="-442" T="1784058628405" />
  <Point X="740" Y="-433" T="1784058628418" />
  <Point X="734" Y="-427" T="1784058628436" />
  <Point X="725" Y="-419" T="1784058628452" />
  <Point X="717" Y="-411" T="1784058628470" />
  <Point X="710" Y="-404" T="1784058628486" />
  <Point X="702" Y="-396" T="1784058628502" />
  <Point X="693" Y="-388" T="1784058628517" />
  <Point X="684" Y="-379" T="1784058628535" />
  <Point X="676" Y="-371" T="1784058628550" />
  <Point X="671" Y="-365" T="1784058628569" />
  <Point X="665" Y="-358" T="1784058628584" />
  <Point X="657" Y="-347" T="1784058628617" />
  <Point X="647" Y="-334" T="1784058628650" />
  <Point X="643" Y="-329" T="1784058628668" />
  <Point X="637" Y="-319" T="1784058628684" />
  <Point X="630" Y="-309" T="1784058628701" />
  <Point X="625" Y="-303" T="1784058628718" />
  <Point X="621" Y="-297" T="1784058628735" />
  <Point X="618" Y="-292" T="1784058628754" />
  <Point X="615" Y="-287" T="1784058628770" />
  <Point X="613" Y="-284" T="1784058628785" />
  <Point X="611" Y="-279" T="1784058628801" />
  <Point X="609" Y="-274" T="1784058628818" />
  <Point X="606" Y="-267" T="1784058628835" />
  <Point X="603" Y="-258" T="1784058628851" />
  <Point X="601" Y="-250" T="1784058628875" />
  <Point X="599" Y="-244" T="1784058628884" />
  <Point X="597" Y="-239" T="1784058628900" />
  <Point X="597" Y="-235" T="1784058628936" />
  <Point X="598" Y="-235" T="1784058628968" />
  <Point X="601" Y="-235" T="1784058628986" />
  <Point X="604" Y="-236" T="1784058629003" />
  <Point X="607" Y="-237" T="1784058629018" />
  <Point X="611" Y="-238" T="1784058629036" />
  <Point X="614" Y="-239" T="1784058629051" />
  <Point X="619" Y="-239" T="1784058629069" />
  <Point X="625" Y="-239" T="1784058629084" />
  <Point X="633" Y="-239" T="1784058629101" />
  <Point X="642" Y="-239" T="1784058629117" />
  <Point X="652" Y="-238" T="1784058629135" />
  <Point X="661" Y="-237" T="1784058629151" />
  <Point X="671" Y="-236" T="1784058629168" />
  <Point X="680" Y="-236" T="1784058629184" />
  <Point X="688" Y="-236" T="1784058629202" />
  <Point X="695" Y="-236" T="1784058629221" />
  <Point X="702" Y="-236" T="1784058629240" />
  <Point X="708" Y="-237" T="1784058629252" />
  <Point X="713" Y="-238" T="1784058629272" />
  <Point X="718" Y="-239" T="1784058629285" />
  <Point X="722" Y="-240" T="1784058629302" />
  <Point X="725" Y="-241" T="1784058629319" />
  <Point X="730" Y="-242" T="1784058629335" />
  <Point X="734" Y="-243" T="1784058629350" />
  <Point X="739" Y="-244" T="1784058629368" />
  <Point X="743" Y="-244" T="1784058629384" />
  <Point X="748" Y="-244" T="1784058629402" />
  <Point X="752" Y="-244" T="1784058629418" />
  <Point X="756" Y="-244" T="1784058629436" />
  <Point X="759" Y="-244" T="1784058629454" />
  <Point X="763" Y="-244" T="1784058629468" />
  <Point X="775" Y="-244" T="1784058629502" />
  <Point X="783" Y="-243" T="1784058629517" />
  <Point X="790" Y="-243" T="1784058629536" />
  <Point X="797" Y="-242" T="1784058629551" />
  <Point X="803" Y="-242" T="1784058629569" />
  <Point X="808" Y="-242" T="1784058629589" />
  <Point X="812" Y="-241" T="1784058629604" />
  <Point X="816" Y="-241" T="1784058629618" />
  <Point X="821" Y="-241" T="1784058629639" />
  <Point X="827" Y="-241" T="1784058629650" />
  <Point X="833" Y="-241" T="1784058629667" />
  <Point X="839" Y="-241" T="1784058629685" />
  <Point X="845" Y="-241" T="1784058629701" />
  <Point X="850" Y="-241" T="1784058629718" />
  <Point X="865" Y="-240" T="1784058629785" />
  <Point X="867" Y="-240" T="1784058629800" />
  <Point X="869" Y="-240" T="1784058629817" />
  <Point X="870" Y="-240" T="1784058629836" />
  <Point X="871" Y="-240" T="1784058629852" />
  <Point X="872" Y="-240" T="1784058629875" />
  <Point X="873" Y="-240" T="1784058629886" />
  <Point X="874" Y="-240" T="1784058629917" />
</Gesture>