<?xml version='1.0' encoding='utf-8'?>
<Gesture Name="Z" NumPts="95">
  <Point X="612" Y="-560" T="1784058634368" />
  <Point X="612" Y="-561" T="1784058634384" />
  <Point X="613" Y="-561" T="1784058634502" />
  <Point X="615" Y="-561" T="1784058634518" />
  <Point X="621" Y="-561" T="1784058634535" />
  <Point X="638" Y="-561" T="1784058634551" />
  <Point X="753" Y="-561" T="1784058634617" />
  <Point X="774" Y="-561" T="1784058634636" />
  <Point X="789" Y="-561" T="1784058634652" />
  <Point X="802" Y="-560" T="1784058634667" />
  <Point X="813" Y="-558" T="1784058634684" />
  <Point X="824" Y="-555" T="1784058634703" />
  <Point X="836" Y="-551" T="1784058634718" />
  <Point X="850" Y="-547" T="1784058634735" />
  <Point X="863" Y="-542" T="1784058634751" />
  <Point X="874" Y="-538" T="1784058634768" />
  <Point X="883" Y="-534" T="1784058634784" />
  <Point X="889" Y="-530" T="1784058634818" />
  <Point X="890" Y="-526" T="1784058634885" />
  <Point X="888" Y="-524" T="1784058634903" />
  <Point X="886" Y="-522" T="1784058634918" />
  <Point X="884" Y="-520" T="1784058634936" />
  <Point X="881" Y="-518" T="1784058634952" />
  <Point X="879" Y="-516" T="1784058634970" />
  <Point X="877" Y="-514" T="1784058634984" />
  <Point X="875" Y="-513" T="1784058635000" />
  <Point X="873" Y="-511" T="1784058635017" />
  <Point X="872" Y="-510" T="1784058635034" />
  <Point X="872" Y="-509" T="1784058635050" />
  <Point X="871" Y="-508" T="1784058635067" />
  <Point X="871" Y="-507" T="1784058635084" />
  <Point X="870" Y="-505" T="1784058635101" />
  <Point X="867" Y="-499" T="1784058635117" />
  <Point X="864" Y="-491" T="1784058635136" />
  <Point X="859" Y="-482" T="1784058635151" />
  <Point X="855" Y="-474" T="1784058635168" />
  <Point X="851" Y="-468" T="1784058635187" />
  <Point X="848" Y="-463" T="1784058635204" />
  <Point X="844" Y="-459" T="1784058635218" />
  <Point X="840" Y="-454" T="1784058635234" />
  <Point X="834" Y="-448" T="1784058635251" />
  <Point X="826" Y="-439" T="1784058635269" />
  <Point X="817" Y="-431" T="1784058635285" />
  <Point X="811" Y="-425" T="1784058635301" />
  <Point X="805" Y="-421" T="1784058635317" />
  <Point X="800" Y="-418" T="1784058635335" />
  <Point X="796" Y="-416" T="1784058635351" />
  <Point X="790" Y="-413" T="1784058635367" />
  <Point X="782" Y="-408" T="1784058635384" />
  <Point X="761" Y="-392" T="1784058635418" />
  <Point X="748" Y="-382" T="1784058635435" />
  <Point X="734" Y="-369" T="1784058635463" />
  <Point X="721" Y="-357" T="1784058635469" />
  <Point X="708" Y="-345" T="1784058635484" />
  <Point X="695" Y="-332" T="1784058635502" />
  <Point X="684" Y="-319" T="1784058635521" />
  <Point X="672" Y="-305" T="1784058635536" />
  <Point X="661" Y="-292" T="1784058635551" />
  <Point X="647" Y="-275" T="1784058635569" />
  <Point X="635" Y="-259" T="1784058635586" />
  <Point X="623" Y="-243" T="1784058635601" />
  <Point X="615" Y="-229" T="1784058635617" />
  <Point X="608" Y="-218" T="1784058635634" />
  <Point X="603" Y="-208" T="1784058635650" />
  <Point X="599" Y="-195" T="1784058635684" />
  <Point X="599" Y="-190" T="1784058635702" />
  <Point X="599" Y="-185" T="1784058635736" />
  <Point X="601" Y="-184" T="1784058635751" />
  <Point X="603" Y="-183" T="1784058635769" />
  <Point X="607" Y="-183" T="1784058635785" />
  <Point X="610" Y="-183" T="1784058635802" />
  <Point X="616" Y="-183" T="1784058635818" />
  <Point X="624" Y="-183" T="1784058635835" />
  <Point X="637" Y="-184" T="1784058635851" />
  <Point X="652" Y="-185" T="1784058635868" />
  <Point X="669" Y="-185" T="1784058635885" />
  <Point X="686" Y="-186" T="1784058635902" />
  <Point X="702" Y="-188" T="1784058635918" />
  <Point X="719" Y="-190" T="1784058635934" />
  <Point X="738" Y="-193" T="1784058635950" />
  <Point X="758" Y="-196" T="1784058635969" />
  <Point X="773" Y="-198" T="1784058635984" />
  <Point X="785" Y="-200" T="1784058636001" />
  <Point X="794" Y="-201" T="1784058636021" />
  <Point X="801" Y="-201" T="1784058636037" />
  <Point X="808" Y="-202" T="1784058636053" />
  <Point X="817" Y="-203" T="1784058636071" />
  <Point X="830" Y="-204" T="1784058636084" />
  <Point X="848" Y="-206" T="1784058636101" />
  <Point X="863" Y="-206" T="1784058636119" />
  <Point X="875" Y="-207" T="1784058636136" />
  <Point X="883" Y="-207" T="1784058636152" />
  <Point X="887" Y="-208" T="1784058636169" />
  <Point X="889" Y="-208" T="1784058636184" />
  <Point X="890" Y="-208" T="1784058636202" />
</Gesture>